{
  "heading": "Oral-History.Digital",
  "text": "Erschließungs- und Recherche-Plattform für Audio- oder Video-Interviews mit Zeitzeuginnen und Zeitzeugen",
  "buttons": {
    "primary": {
      "label": "Archive und Sammlungen",
      "target": "/de/catalog",
      "description": "Hier finden Sie die Archive und Sammlungen, die Oral-History-Digital bereits erschlossen hat."
    },
    "secondary": {
      "label": "Institutionen",
      "target": "/de/catalog/institutions",
      "description": "Hier finden Sie die Institutionen und Einrichtungen, die Archive und Sammlungen in Oral-History-Digital bereitstellen."
    }
  }
}
